fastapi_csrf_jinja/__init__.py
fastapi_csrf_jinja/jinja_processor.py
fastapi_csrf_jinja/middleware.py
fastapi_csrf_jinja-0.1.3.dist-info/LICENSE
fastapi_csrf_jinja-0.1.3.dist-info/METADATA
fastapi_csrf_jinja-0.1.3.dist-info/WHEEL
fastapi_csrf_jinja-0.1.3.dist-info/RECORD
