Metadata-Version: 2.1
Name: fastapi-csrf-jinja
Version: 0.1.3
Summary: CSRF middleware for FastAPI applications with Jinja template integration.
Home-page: https://github.com/lainezdev/fastapi-csrf-jinja
License: MIT
Keywords: fastapi,csrf,jinja,middleware
Author: Juan Lainez
Author-email: camilolainez@gmail.com
Requires-Python: >=3.8
Classifier: Development Status :: 4 - Beta
Classifier: Environment :: Web Environment
Classifier: Framework :: FastAPI
Classifier: Intended Audience :: Developers
Classifier: Intended Audience :: Information Technology
Classifier: License :: OSI Approved :: MIT License
Classifier: Operating System :: OS Independent
Classifier: Programming Language :: Python :: 3
Classifier: Programming Language :: Python :: 3.8
Classifier: Programming Language :: Python :: 3.9
Classifier: Programming Language :: Python :: 3.10
Classifier: Programming Language :: Python :: 3.11
Classifier: Programming Language :: Python :: 3.12
Classifier: Programming Language :: Python :: 3 :: Only
Classifier: Topic :: Internet :: WWW/HTTP
Classifier: Topic :: Internet :: WWW/HTTP :: HTTP Servers
Classifier: Topic :: Software Development :: Libraries
Classifier: Topic :: Software Development :: Libraries :: Application Frameworks
Classifier: Topic :: Software Development :: Libraries :: Python Modules
Classifier: Typing :: Typed
Requires-Dist: itsdangerous (>=2.0.1,<3.0.0)
Requires-Dist: starlette (>=0.14.2)
Requires-Dist: typing-extensions (>=4.8.0)
Project-URL: Documentation, https://github.com/lainezdev/fastapi-csrf-jinja
Project-URL: Repository, https://github.com/lainezdev/fastapi-csrf-jinja
Project-URL: Source, https://github.com/lainezdev/fastapi-csrf-jinja
